generate_omero_objects.py
generate_xml.py
omero_cli_transfer.py
omero/plugins/transfer.py
omero_cli_transfer-1.3.1.dist-info/licenses/LICENSE
omero_cli_transfer-1.3.1.dist-info/METADATA
omero_cli_transfer-1.3.1.dist-info/WHEEL
omero_cli_transfer-1.3.1.dist-info/top_level.txt
omero_cli_transfer-1.3.1.dist-info/RECORD
