Metadata-Version: 2.4
Name: omero-cli-transfer
Version: 1.3.1
Summary: A set of utilities for exporting a transfer packet from an OMERO server and importing it in a different server.
Maintainer-email: Erick Ratamero <erick.ratamero@embl.de>
License-Expression: GPL-2.0
Project-URL: Repository, https://github.com/TheJacksonLaboratory/omero-cli-transfer
Requires-Python: >=3.9
License-File: LICENSE
Requires-Dist: ezomero<4.0.0,>=3.1.0
Requires-Dist: ome-types<0.7.0,>=0.6.1
Provides-Extra: rocrate
Requires-Dist: rocrate<1.0.0,>=0.7.0; extra == "rocrate"
Dynamic: license-file
